lambda_universal_router/__init__.py
lambda_universal_router/base.py
lambda_universal_router/handlers.py
lambda_universal_router/router.py
lambda_universal_router/events/__init__.py
lambda_universal_router/events/api_gateway.py
lambda_universal_router/events/custom.py
lambda_universal_router/events/dynamodb.py
lambda_universal_router/events/eventbridge.py
lambda_universal_router/events/kafka.py
lambda_universal_router/events/kinesis.py
lambda_universal_router/events/s3.py
lambda_universal_router/events/sns.py
lambda_universal_router/events/sqs.py
lambda_universal_router-1.0.0.dist-info/licenses/LICENSE
tests/__init__.py
tests/test_router.py
lambda_universal_router-1.0.0.dist-info/METADATA
lambda_universal_router-1.0.0.dist-info/WHEEL
lambda_universal_router-1.0.0.dist-info/top_level.txt
lambda_universal_router-1.0.0.dist-info/RECORD
