Metadata-Version: 2.4
Name: lambda-universal-router
Version: 1.0.0
Summary: A flexible AWS Lambda event router with support for multiple event sources
Home-page: https://github.com/raumildhandhukia/lambda-universal-router
Author: Raumil Dhandhukia
Author-email: raumild@gmail.com
Project-URL: Documentation, https://raumildhandhukia.github.io/lambda-universal-router/
Project-URL: Source, https://github.com/raumildhandhukia/lambda-universal-router
Project-URL: Changelog, https://raumildhandhukia.github.io/lambda-universal-router/changelog
Project-URL: Contributing, https://raumildhandhukia.github.io/lambda-universal-router/contributing
Project-URL: License, https://github.com/raumildhandhukia/lambda-universal-router/blob/main/LICENSE
Project-URL: Issue Tracker, https://github.com/raumildhandhukia/lambda-universal-router/issues
Classifier: Development Status :: 5 - Production/Stable
Classifier: Intended Audience :: Developers
Classifier: License :: OSI Approved :: MIT License
Classifier: Programming Language :: Python :: 3
Classifier: Programming Language :: Python :: 3.7
Classifier: Programming Language :: Python :: 3.8
Classifier: Programming Language :: Python :: 3.9
Classifier: Programming Language :: Python :: 3.10
Classifier: Programming Language :: Python :: 3.11
Classifier: Programming Language :: Python :: 3.12
Classifier: Programming Language :: Python :: 3.13
Requires-Python: >=3.7
License-File: LICENSE
Dynamic: author
Dynamic: author-email
Dynamic: classifier
Dynamic: description
Dynamic: description-content-type
Dynamic: home-page
Dynamic: license-file
Dynamic: project-url
Dynamic: requires-python
Dynamic: summary
